shamo/__init__.py
shamo/cli/__init__.py
shamo/cli/report.py
shamo/core/__init__.py
shamo/core/distributions/__init__.py
shamo/core/distributions/abc.py
shamo/core/distributions/constant.py
shamo/core/distributions/normal.py
shamo/core/distributions/uniform.py
shamo/core/fem/__init__.py
shamo/core/fem/fem.py
shamo/core/fem/field.py
shamo/core/fem/group.py
shamo/core/fem/tissue.py
shamo/core/fem/sensors/__init__.py
shamo/core/fem/sensors/abc.py
shamo/core/fem/sensors/point.py
shamo/core/fem/sensors/surface.py
shamo/core/objects/__init__.py
shamo/core/objects/abc.py
shamo/core/objects/dir.py
shamo/core/objects/file.py
shamo/core/problems/__init__.py
shamo/core/problems/parametric/__init__.py
shamo/core/problems/parametric/abc.py
shamo/core/problems/parametric/getdp.py
shamo/core/problems/parametric/components/__init__.py
shamo/core/problems/parametric/components/tissue_property.py
shamo/core/problems/parametric/components/value.py
shamo/core/problems/single/__init__.py
shamo/core/problems/single/abc.py
shamo/core/problems/single/getdp.py
shamo/core/problems/single/components/__init__.py
shamo/core/problems/single/components/abc.py
shamo/core/problems/single/components/file_path.py
shamo/core/problems/single/components/grid_sampler.py
shamo/core/problems/single/components/sensors.py
shamo/core/problems/single/components/tissue_property.py
shamo/core/problems/single/components/tissues.py
shamo/core/solutions/__init__.py
shamo/core/solutions/parametric/__init__.py
shamo/core/solutions/parametric/abc.py
shamo/core/solutions/parametric/getdp.py
shamo/core/solutions/single/__init__.py
shamo/core/solutions/single/getdp.py
shamo/core/surrogate/__init__.py
shamo/core/surrogate/abc.py
shamo/core/surrogate/masked_scalar.py
shamo/core/surrogate/scalar.py
shamo/eeg/__init__.py
shamo/eeg/leadfield/__init__.py
shamo/eeg/leadfield/parametric/__init__.py
shamo/eeg/leadfield/parametric/problem.py
shamo/eeg/leadfield/parametric/solution.py
shamo/eeg/leadfield/parametric/surrogate.py
shamo-1.2.1.dist-info/LICENSE.md
shamo-1.2.1.dist-info/METADATA
shamo-1.2.1.dist-info/WHEEL
shamo-1.2.1.dist-info/entry_points.txt
shamo-1.2.1.dist-info/top_level.txt
shamo-1.2.1.dist-info/RECORD
