Metadata-Version: 2.1
Name: shamo
Version: 1.2.1
Summary: A tool for electromagnetic modelling of the head and sensitivity analysis.
Home-page: https://github.com/CyclotronResearchCentre/shamo
Author: Martin Grignard
Author-email: mar.grignard@uliege.be
License: GPLv3
Project-URL: Bug Tracker, https://github.com/CyclotronResearchCentre/shamo/issues
Project-URL: Changelog, https://github.com/CyclotronResearchCentre/shamo/blob/master/CHANGELOG.md
Keywords: eeg,tdcs,meg,tms,electromagnetics,modelling
Platform: any
Classifier: Development Status :: 3 - Alpha
Classifier: Intended Audience :: Science/Research
Classifier: License :: OSI Approved :: GNU General Public License v3 (GPLv3)
Classifier: Natural Language :: English
Classifier: Operating System :: OS Independent
Classifier: Programming Language :: Python :: 3
Classifier: Programming Language :: Python :: 3.7
Classifier: Programming Language :: Python :: 3.8
Classifier: Programming Language :: Python :: 3.9
Classifier: Topic :: Scientific/Engineering :: Physics
Classifier: Topic :: Scientific/Engineering :: Visualization
Classifier: Topic :: Scientific/Engineering :: Medical Science Apps.
Requires-Python: >=3.7
License-File: LICENSE.md
Requires-Dist: chaospy
Requires-Dist: click
Requires-Dist: gmsh
Requires-Dist: h5py
Requires-Dist: jinja2
Requires-Dist: meshio
Requires-Dist: nibabel
Requires-Dist: nilearn
Requires-Dist: numpy
Requires-Dist: pygalmesh
Requires-Dist: pyyaml
Requires-Dist: SALib
Requires-Dist: scikit-learn
Requires-Dist: scipy
Requires-Dist: wurlitzer
